{
  "schemaVersion": 1,
  "id": "custom-gamerules",
  "version": "${version}",
  "name": "Custom Gamerules API",
  "icon": "assets/custom-gamerules/icon.png",
  "description": "An API that provides ways to register gamerules and a menu",
  "licence": "MIT",
  "contact": {
    "sources": "https://github.com/MisterPeModder/CustomGameRules",
    "issues": "https://github.com/MisterPeModder/CustomGameRules/issues",
    "maven": "https://maven.misterpemodder.com/libs-release/com/misterpemodder/custom-gamerules/"
  },
  "environment": "*",
  "mixins": [
    "custom-gamerules.client.json",
    "custom-gamerules.common.json"
  ],
  "requires": {
    "fabricloader": ">=0.4.0"
  },
  "custom": {
    "modmenu:api": true
  }
}